remotezip.py
remotezip-0.12.3.dist-info/LICENSE
remotezip-0.12.3.dist-info/METADATA
remotezip-0.12.3.dist-info/WHEEL
remotezip-0.12.3.dist-info/entry_points.txt
remotezip-0.12.3.dist-info/top_level.txt
remotezip-0.12.3.dist-info/RECORD
